materforge/__init__.py
materforge/_version.py
materforge/py.typed
materforge/algorithms/__init__.py
materforge/algorithms/interpolation.py
materforge/algorithms/piecewise_builder.py
materforge/algorithms/piecewise_inverter.py
materforge/algorithms/regression_processor.py
materforge/core/__init__.py
materforge/core/elements.py
materforge/core/exceptions.py
materforge/core/materials.py
materforge/core/symbol_registry.py
materforge/data/__init__.py
materforge/data/constants/__init__.py
materforge/data/constants/physical_constants.py
materforge/data/constants/processing_constants.py
materforge/data/elements/__init__.py
materforge/data/elements/element_data.py
materforge/data/materials/__init__.py
materforge/data/materials/alloys/__init__.py
materforge/data/materials/alloys/1.4301/1.4301.xlsx
materforge/data/materials/alloys/1.4301/1.4301.yaml
materforge/data/materials/alloys/1.4301/__init__.py
materforge/data/materials/pure_metals/__init__.py
materforge/data/materials/pure_metals/Al/Al.yaml
materforge/data/materials/pure_metals/Al/__init__.py
materforge/parsing/__init__.py
materforge/parsing/api.py
materforge/parsing/config/__init__.py
materforge/parsing/config/material_yaml_parser.py
materforge/parsing/config/yaml_keys.py
materforge/parsing/io/__init__.py
materforge/parsing/io/data_handler.py
materforge/parsing/processors/__init__.py
materforge/parsing/processors/computed_property_processor.py
materforge/parsing/processors/dependency_resolver.py
materforge/parsing/processors/post_processor.py
materforge/parsing/processors/property_handlers.py
materforge/parsing/processors/property_processor.py
materforge/parsing/processors/property_processor_base.py
materforge/parsing/utils/__init__.py
materforge/parsing/utils/utilities.py
materforge/parsing/validation/__init__.py
materforge/parsing/validation/array_validator.py
materforge/parsing/validation/errors.py
materforge/parsing/validation/property_type_detector.py
materforge/parsing/validation/property_validator.py
materforge-0.6.3.dist-info/licenses/AUTHORS.txt
materforge-0.6.3.dist-info/licenses/LICENSE
materforge-0.6.3.dist-info/METADATA
materforge-0.6.3.dist-info/WHEEL
materforge-0.6.3.dist-info/entry_points.txt
materforge-0.6.3.dist-info/top_level.txt
materforge-0.6.3.dist-info/RECORD
