Metadata-Version: 2.4
Name: materforge
Version: 0.6.3
Summary: A high-performance Python library for material simulation and analysis
Author-email: Rahil Doshi <rahil.doshi@fau.de>
Maintainer-email: Rahil Doshi <rahil.doshi@fau.de>
License: BSD 3-Clause License
Project-URL: Homepage, https://github.com/rahildoshi97/materforge
Project-URL: Repository, https://github.com/rahildoshi97/materforge
Project-URL: Bug Tracker, https://github.com/rahildoshi97/materforge/issues
Project-URL: Documentation, https://materforge.readthedocs.io
Project-URL: Changelog, https://github.com/rahildoshi97/materforge/blob/main/CHANGELOG.md
Project-URL: GitLab Mirror, https://i10git.cs.fau.de/rahil.doshi/materforge
Keywords: materials,thermophysical,properties,yaml,scientific-computing,piecewise,regression,sympy
Classifier: Development Status :: 4 - Beta
Classifier: Intended Audience :: Science/Research
Classifier: Intended Audience :: Developers
Classifier: License :: OSI Approved :: BSD License
Classifier: Operating System :: OS Independent
Classifier: Programming Language :: Python :: 3
Classifier: Programming Language :: Python :: 3.10
Classifier: Programming Language :: Python :: 3.11
Classifier: Programming Language :: Python :: 3.12
Classifier: Programming Language :: Python :: 3.13
Classifier: Topic :: Scientific/Engineering :: Physics
Classifier: Topic :: Scientific/Engineering
Requires-Python: >=3.10
License-File: LICENSE
License-File: AUTHORS.txt
Requires-Dist: numpy<3.0.0,>=1.20.0
Requires-Dist: sympy<2.0.0,>=1.9.0
Requires-Dist: scipy<2.0.0,>=1.7.0
Requires-Dist: matplotlib<4.0.0,>=3.5.0
Requires-Dist: ruamel.yaml<1.0.0,>=0.17.0
Requires-Dist: pandas<3.0.0,>=1.4.0
Requires-Dist: openpyxl>=3.1.5
Requires-Dist: pwlf<3.0.0,>=2.5.1
Provides-Extra: dev
Requires-Dist: pytest>=7.0.0; extra == "dev"
Requires-Dist: pytest-xdist>=3.0.0; extra == "dev"
Requires-Dist: pytest-mock>=3.10.0; extra == "dev"
Requires-Dist: hypothesis>=6.0.0; extra == "dev"
Requires-Dist: black>=23.0.0; extra == "dev"
Requires-Dist: isort>=5.12.0; extra == "dev"
Requires-Dist: flake8>=6.0.0; extra == "dev"
Requires-Dist: mypy>=1.0.0; extra == "dev"
Requires-Dist: pre-commit>=3.0.0; extra == "dev"
Requires-Dist: ruff>=0.1.0; extra == "dev"
Provides-Extra: test
Requires-Dist: pytest>=7.0.0; extra == "test"
Requires-Dist: pytest-xdist>=3.0.0; extra == "test"
Requires-Dist: pytest-mock>=3.10.0; extra == "test"
Requires-Dist: hypothesis>=6.0.0; extra == "test"
Requires-Dist: pytest-benchmark>=4.0.0; extra == "test"
Provides-Extra: docs
Requires-Dist: sphinx>=6.0.0; extra == "docs"
Requires-Dist: sphinx-rtd-theme>=1.2.0; extra == "docs"
Requires-Dist: myst-parser>=1.0.0; extra == "docs"
Requires-Dist: sphinx-autodoc-typehints>=1.20.0; extra == "docs"
Requires-Dist: sphinx-copybutton>=0.5.2; extra == "docs"
Requires-Dist: linkify-it-py>=0.7.1; extra == "docs"
Provides-Extra: performance
Requires-Dist: line_profiler>=4.0.0; extra == "performance"
Requires-Dist: memory_profiler>=0.60.0; extra == "performance"
Requires-Dist: pytest-benchmark>=4.0.0; extra == "performance"
Provides-Extra: simulation
Requires-Dist: pystencils>=1.3.0; extra == "simulation"
Provides-Extra: all
Requires-Dist: materforge[dev,docs,performance,simulation,test]; extra == "all"
Dynamic: license-file
